boka_tools/__init__.py
boka_tools/planning/__init__.py
boka_tools/planning/gantt.py
boka_tools/planning/primavera.py
boka_tools/soil_investigation/__init__.py
boka_tools/soil_investigation/ags.py
boka_tools/soil_investigation/boiler_plates/__init__.py
boka_tools/soil_investigation/boiler_plates/gef.py
boka_tools/soil_investigation/boiler_plates/gint.py
boka_tools/soil_investigation/boiler_plates/legends_styles.py
boka_tools/soil_investigation/boiler_plates/standard_axes.py
boka_tools/soil_investigation/json/__init__.py
boka_tools/soil_investigation/json/ags3_to_gint.json
boka_tools/soil_investigation/json/ags4.min.json
boka_tools/soil_investigation/json/ags4_to_gint.json
boka_tools/soil_investigation/json/GEOL_LEG.json
boka_tools/soil_investigation/legacy_plot.py
boka_tools/soil_investigation/plot.py
boka_tools/soil_investigation/plot_props_schema.py
boka_tools/soil_investigation/sql/__init__.py
boka_tools/soil_investigation/sql/bh-data.sql
boka_tools/soil_investigation/sql/gint_sql.py
boka_tools/soil_investigation/sql/lab-data.sql
boka_tools/soil_investigation/sql/point-data.sql
boka_tools/soil_investigation/sql/sql-cpt-bh-5m.sql
boka_tools/utils/__init__.py
boka_tools/utils/sql.py
boka_tools-0.3.0.dist-info/WHEEL
boka_tools-0.3.0.dist-info/METADATA
boka_tools-0.3.0.dist-info/RECORD
