Metadata-Version: 2.1
Name: boka-tools
Version: 0.3.0
Summary: package for general automation work at Boskalis
License: MIT
Author: Maarten Betman
Author-email: maarten.betman@boskalis.com
Requires-Python: >=3.7.1,<3.11
Classifier: License :: OSI Approved :: MIT License
Classifier: Programming Language :: Python :: 3
Classifier: Programming Language :: Python :: 3.10
Classifier: Programming Language :: Python :: 3.8
Classifier: Programming Language :: Python :: 3.9
Requires-Dist: SQLAlchemy (==1.4.27)
Requires-Dist: pandas (>=1.3.4,<2.0.0)
